github_actions_cdk/aws_cdk/__init__.py
github_actions_cdk/aws_cdk/py.typed
github_actions_cdk/aws_cdk/_jsii/__init__.py
github_actions_cdk/aws_cdk/_jsii/aws-cdk@0.0.23.jsii.tgz
github_actions_cdk.aws_cdk-0.0.23.dist-info/LICENSE
github_actions_cdk.aws_cdk-0.0.23.dist-info/METADATA
github_actions_cdk.aws_cdk-0.0.23.dist-info/WHEEL
github_actions_cdk.aws_cdk-0.0.23.dist-info/top_level.txt
github_actions_cdk.aws_cdk-0.0.23.dist-info/RECORD
