Metadata-Version: 2.1
Name: github-actions-cdk.aws-cdk
Version: 0.0.23
Summary: A TypeScript library for building GitHub Actions pipelines specifically for AWS CDK applications. This library allows developers to define, structure, and automate CI/CD workflows tailored to CDK projects, making it easy to deploy infrastructure through GitHub Actions in a type-safe and modular way.
Home-page: https://github.com/hupe1980/github-actions-cdk.git
Author: hupe1980
License: MIT
Project-URL: Source, https://github.com/hupe1980/github-actions-cdk.git
Classifier: Intended Audience :: Developers
Classifier: Operating System :: OS Independent
Classifier: Programming Language :: JavaScript
Classifier: Programming Language :: Python :: 3 :: Only
Classifier: Programming Language :: Python :: 3.8
Classifier: Programming Language :: Python :: 3.9
Classifier: Programming Language :: Python :: 3.10
Classifier: Programming Language :: Python :: 3.11
Classifier: Typing :: Typed
Classifier: Development Status :: 4 - Beta
Classifier: License :: OSI Approved
Requires-Python: ~=3.8
License-File: LICENSE
Requires-Dist: aws-cdk-lib<3.0.0,>=2.164.1
Requires-Dist: constructs<11.0.0,>=10.4.2
Requires-Dist: github-actions-cdk<0.0.24,>=0.0.23
Requires-Dist: jsii<2.0.0,>=1.104.0
Requires-Dist: publication>=0.0.3
Requires-Dist: typeguard<4.3.0,>=2.13.3
